MANIFEST.in
setup.cfg
setup.py
pyarp/__init__.py
pyarp/__main__.py
pyarp/pyarplib.py
pyarp.egg-info/PKG-INFO
pyarp.egg-info/SOURCES.txt
pyarp.egg-info/dependency_links.txt
pyarp.egg-info/entry_points.txt
pyarp.egg-info/requires.txt
pyarp.egg-info/top_level.txt
pyarp/data/MANUAL.txt