Metadata-Version: 1.1
Name: pyarp
Version: 0.1.2
Summary: A user-friendly ARP spoofing tool
Home-page: https://github.com/7BISSO/python-arp-spoofer
Author: Imad Hsissou
Author-email: imad.hsissou@gmail.com
License: MIT
Download-URL: https://github.com/7BISSO/python-arp-spoofer/tarball/0.1.1
Keywords: arp,scapy
Platform: UNKNOWN
